README
setup.py
./dokuwiki2html
PyDokuwiki.egg-info/PKG-INFO
PyDokuwiki.egg-info/SOURCES.txt
PyDokuwiki.egg-info/dependency_links.txt
PyDokuwiki.egg-info/top_level.txt
dokuwiki/__init__.py
dokuwiki/dokuwikixmlrpc.py
dokuwiki/elements.py
dokuwiki/html.py
dokuwiki/parsers.py
dokuwiki/util.py