Metadata-Version: 1.0
Name: PyDokuwiki
Version: 0.1
Summary: Python module and scripts for manipulating dokuwiki formated text (seen in dokuwiki's wiki pages etc).
Home-page: UNKNOWN
Author: Stefan Nozinic
Author-email: stefan@lugons.org
License: UNKNOWN
Keywords: wiki dokuwiki text parsing
Platform: UNKNOWN
